{
  "__inputs": [],
  "__requires": [],
  "annotations": {
    "list": [
      {
        "builtIn": 1,
        "datasource": {
          "type": "grafana",
          "uid": "-- Grafana --"
        },
        "enable": true,
        "hide": true,
        "iconColor": "rgba(0, 211, 255, 1)",
        "name": "Annotations & Alerts",
        "type": "dashboard"
      }
    ]
  },
  "description": "GPU fleet secondary-market economics: NPV vs liquidation value, live market prices, and fleet sell signals.",
  "editable": true,
  "fiscalYearStartMonth": 0,
  "graphTooltip": 1,
  "id": null,
  "links": [],
  "liveNow": false,
  "panels": [
    {
      "id": 1,
      "type": "text",
      "title": "GPU Fleet Economics \u00b7 Secondary Market",
      "gridPos": {
        "h": 3,
        "w": 24,
        "x": 0,
        "y": 0
      },
      "options": {
        "mode": "markdown",
        "content": "## \ud83d\udcb0 GPU Fleet Economics \u00b7 Secondary Market\n\nCompares **Operational NPV** (present value of keeping the GPU) vs **Secondary Market Value** (liquidation price) for each GPU in the fleet.\n\n- **NPV Keep** = discounted future revenue from continued GPU operation\n- **NPV Sell** = expected net proceeds from secondary market sale today\n- **Sell Signal** = triggered when NPV Sell > NPV Keep \u00d7 1.05 (5% margin)\n\n> Live market prices are fetched every 6 hours from JarvisLabs and cross-referenced with secondary-market listings.",
        "code": {
          "language": "plaintext",
          "showLineNumbers": false,
          "showMiniMap": false
        }
      },
      "transparent": false,
      "datasource": null
    },
    {
      "id": 2,
      "type": "stat",
      "title": "Fleet Secondary Value",
      "description": "Total liquidation value of fleet (sum of NPV Sell across all GPUs)",
      "gridPos": {
        "h": 4,
        "w": 5,
        "x": 0,
        "y": 3
      },
      "datasource": {
        "type": "postgres",
        "uid": "P0D1C26D7DC78F49D"
      },
      "targets": [
        {
          "refId": "A",
          "rawSql": "SELECT NOW() as time, SUM(d.npv_sell) as value FROM gpu_economic_decisions d JOIN gpu_datacenter_mapping dm ON d.gpu_uuid = dm.gpu_uuid WHERE d.time = (SELECT MAX(time) FROM gpu_economic_decisions WHERE gpu_uuid = d.gpu_uuid) AND ('$datacenter' = 'ALL' OR dm.datacenter = '$datacenter')",
          "format": "table"
        }
      ],
      "options": {
        "reduceOptions": {
          "values": false,
          "calcs": [
            "lastNotNull"
          ],
          "fields": ""
        },
        "orientation": "auto",
        "textMode": "value",
        "colorMode": "value",
        "graphMode": "none",
        "justifyMode": "center"
      },
      "fieldConfig": {
        "defaults": {
          "unit": "currencyUSD",
          "decimals": 0,
          "color": {
            "mode": "fixed",
            "fixedColor": "#3fb950"
          },
          "thresholds": {
            "mode": "absolute",
            "steps": [
              {
                "value": null,
                "color": "#3fb950"
              }
            ]
          },
          "mappings": []
        },
        "overrides": []
      },
      "transparent": false
    },
    {
      "id": 3,
      "type": "stat",
      "title": "Sell Signals",
      "description": "Number of GPUs where secondary market value exceeds operational NPV",
      "gridPos": {
        "h": 4,
        "w": 4,
        "x": 5,
        "y": 3
      },
      "datasource": {
        "type": "postgres",
        "uid": "P0D1C26D7DC78F49D"
      },
      "targets": [
        {
          "refId": "A",
          "rawSql": "SELECT NOW() as time, COUNT(*) as value FROM gpu_economic_decisions d JOIN gpu_datacenter_mapping dm ON d.gpu_uuid = dm.gpu_uuid WHERE d.decision = 'sell' AND d.time = (SELECT MAX(time) FROM gpu_economic_decisions WHERE gpu_uuid = d.gpu_uuid) AND ('$datacenter' = 'ALL' OR dm.datacenter = '$datacenter')",
          "format": "table"
        }
      ],
      "options": {
        "reduceOptions": {
          "values": false,
          "calcs": [
            "lastNotNull"
          ],
          "fields": ""
        },
        "orientation": "auto",
        "textMode": "value_and_name",
        "colorMode": "background",
        "graphMode": "none",
        "justifyMode": "center"
      },
      "fieldConfig": {
        "defaults": {
          "unit": "short",
          "decimals": 0,
          "thresholds": {
            "mode": "absolute",
            "steps": [
              {
                "value": null,
                "color": "#3fb950"
              },
              {
                "value": 1,
                "color": "#d29922"
              },
              {
                "value": 3,
                "color": "#f85149"
              }
            ]
          },
          "color": {
            "mode": "thresholds"
          },
          "mappings": []
        },
        "overrides": []
      },
      "transparent": false
    },
    {
      "id": 4,
      "type": "stat",
      "title": "A100 Market Price (Live)",
      "description": "Latest secondary market mid-price for NVIDIA A100-SXM4-80GB (used, good condition)",
      "gridPos": {
        "h": 4,
        "w": 5,
        "x": 9,
        "y": 3
      },
      "datasource": {
        "type": "postgres",
        "uid": "P0D1C26D7DC78F49D"
      },
      "targets": [
        {
          "refId": "A",
          "rawSql": "SELECT NOW() as time, price_mid_usd as value FROM v_latest_market_prices WHERE model LIKE '%A100%' AND condition = 'used_good' LIMIT 1",
          "format": "table"
        }
      ],
      "options": {
        "reduceOptions": {
          "values": false,
          "calcs": [
            "lastNotNull"
          ],
          "fields": ""
        },
        "orientation": "auto",
        "textMode": "value",
        "colorMode": "value",
        "graphMode": "none",
        "justifyMode": "center"
      },
      "fieldConfig": {
        "defaults": {
          "unit": "currencyUSD",
          "decimals": 0,
          "displayName": "~${__value.text}",
          "color": {
            "mode": "fixed",
            "fixedColor": "#3fb950"
          },
          "thresholds": {
            "mode": "absolute",
            "steps": [
              {
                "value": null,
                "color": "#3fb950"
              }
            ]
          },
          "mappings": []
        },
        "overrides": []
      },
      "transparent": false
    },
    {
      "id": 5,
      "type": "stat",
      "title": "H100 Market Price (Live)",
      "description": "Latest secondary market mid-price for NVIDIA H100-SXM5-80GB (used, good condition)",
      "gridPos": {
        "h": 4,
        "w": 5,
        "x": 14,
        "y": 3
      },
      "datasource": {
        "type": "postgres",
        "uid": "P0D1C26D7DC78F49D"
      },
      "targets": [
        {
          "refId": "A",
          "rawSql": "SELECT NOW() as time, price_mid_usd as value FROM v_latest_market_prices WHERE model LIKE '%H100%' AND condition = 'used_good' LIMIT 1",
          "format": "table"
        }
      ],
      "options": {
        "reduceOptions": {
          "values": false,
          "calcs": [
            "lastNotNull"
          ],
          "fields": ""
        },
        "orientation": "auto",
        "textMode": "value",
        "colorMode": "value",
        "graphMode": "none",
        "justifyMode": "center"
      },
      "fieldConfig": {
        "defaults": {
          "unit": "currencyUSD",
          "decimals": 0,
          "color": {
            "mode": "fixed",
            "fixedColor": "#bc8cff"
          },
          "thresholds": {
            "mode": "absolute",
            "steps": [
              {
                "value": null,
                "color": "#bc8cff"
              }
            ]
          },
          "mappings": []
        },
        "overrides": []
      },
      "transparent": false
    },
    {
      "id": 6,
      "type": "stat",
      "title": "Prices Last Updated",
      "description": "Timestamp of the most recent market price fetch",
      "gridPos": {
        "h": 4,
        "w": 5,
        "x": 19,
        "y": 3
      },
      "datasource": {
        "type": "postgres",
        "uid": "P0D1C26D7DC78F49D"
      },
      "targets": [
        {
          "refId": "A",
          "rawSql": "SELECT NOW() as time, EXTRACT(EPOCH FROM MAX(fetched_at)) * 1000 as value FROM gpu_market_prices",
          "format": "table"
        }
      ],
      "options": {
        "reduceOptions": {
          "values": false,
          "calcs": [
            "lastNotNull"
          ],
          "fields": ""
        },
        "orientation": "auto",
        "textMode": "value",
        "colorMode": "value",
        "graphMode": "none",
        "justifyMode": "center"
      },
      "fieldConfig": {
        "defaults": {
          "unit": "dateTimeFromNow",
          "color": {
            "mode": "fixed",
            "fixedColor": "#58a6ff"
          },
          "thresholds": {
            "mode": "absolute",
            "steps": [
              {
                "value": null,
                "color": "#58a6ff"
              }
            ]
          },
          "mappings": []
        },
        "overrides": []
      },
      "transparent": false
    },
    {
      "id": 10,
      "type": "row",
      "title": "\ud83d\udfe2 A100 \u2014 NVIDIA A100 SXM4-80GB",
      "collapsed": false,
      "gridPos": {
        "h": 1,
        "w": 24,
        "x": 0,
        "y": 7
      },
      "panels": [],
      "datasource": null
    },
    {
      "id": 11,
      "type": "barchart",
      "title": "A100 NPV vs Original Cost",
      "description": "Per-GPU comparison: original purchase cost, secondary market NPV, and operational NPV (keep value)",
      "gridPos": {
        "h": 10,
        "w": 15,
        "x": 0,
        "y": 8
      },
      "datasource": {
        "type": "postgres",
        "uid": "P0D1C26D7DC78F49D"
      },
      "targets": [
        {
          "refId": "A",
          "rawSql": "WITH latest_dec AS (\n  SELECT DISTINCT ON (gpu_uuid)\n    gpu_uuid, npv_keep, npv_sell, decision\n  FROM gpu_economic_decisions\n  ORDER BY gpu_uuid, time DESC\n),\nmkt AS (\n  SELECT DISTINCT ON (model)\n    model, price_mid_usd, original_cost_usd\n  FROM gpu_market_prices\n  WHERE condition = 'used_good'\n  ORDER BY model, fetched_at DESC\n)\nSELECT\n  a.gpu_uuid AS \"GPU\",\n  COALESCE(mp.original_cost_usd, 15000) AS \"Original Cost\",\n  ROUND(COALESCE(d.npv_sell, mp.price_mid_usd * 0.95)::numeric, 0) AS \"Secondary Market (NPV Sell)\",\n  ROUND(COALESCE(d.npv_keep, 0)::numeric, 0) AS \"Operational Value (NPV Keep)\"\nFROM gpu_assets a\nJOIN gpu_datacenter_mapping dm ON a.gpu_uuid = dm.gpu_uuid\nLEFT JOIN latest_dec d ON a.gpu_uuid = d.gpu_uuid\nLEFT JOIN mkt mp ON a.model = mp.model\nWHERE a.model LIKE '%A100%'\n  AND ('$datacenter' = 'ALL' OR dm.datacenter = '$datacenter')\nORDER BY a.gpu_uuid",
          "format": "table"
        }
      ],
      "options": {
        "xField": "GPU",
        "barWidth": 0.6,
        "groupWidth": 0.7,
        "fillOpacity": 85,
        "gradientMode": "none",
        "tooltipOptions": {
          "mode": "multi",
          "sort": "none"
        },
        "legend": {
          "displayMode": "list",
          "placement": "bottom",
          "calcs": []
        },
        "orientation": "auto",
        "stacking": "none",
        "showValue": "never",
        "barRadius": 0.03
      },
      "fieldConfig": {
        "defaults": {
          "unit": "currencyUSD",
          "decimals": 0,
          "color": {
            "mode": "fixed"
          },
          "custom": {
            "axisPlacement": "auto",
            "axisLabel": "",
            "axisColorMode": "text",
            "scaleDistribution": {
              "type": "linear"
            },
            "hideFrom": {
              "legend": false,
              "tooltip": false,
              "viz": false
            },
            "fillOpacity": 85
          }
        },
        "overrides": [
          {
            "matcher": {
              "id": "byName",
              "options": "Original Cost"
            },
            "properties": [
              {
                "id": "color",
                "value": {
                  "mode": "fixed",
                  "fixedColor": "#484f58"
                }
              },
              {
                "id": "unit",
                "value": "currencyUSD"
              },
              {
                "id": "decimals",
                "value": 0
              }
            ]
          },
          {
            "matcher": {
              "id": "byName",
              "options": "Secondary Market (NPV Sell)"
            },
            "properties": [
              {
                "id": "color",
                "value": {
                  "mode": "fixed",
                  "fixedColor": "#3fb950"
                }
              },
              {
                "id": "unit",
                "value": "currencyUSD"
              },
              {
                "id": "decimals",
                "value": 0
              }
            ]
          },
          {
            "matcher": {
              "id": "byName",
              "options": "Operational Value (NPV Keep)"
            },
            "properties": [
              {
                "id": "color",
                "value": {
                  "mode": "fixed",
                  "fixedColor": "#1f6feb"
                }
              },
              {
                "id": "unit",
                "value": "currencyUSD"
              },
              {
                "id": "decimals",
                "value": 0
              }
            ]
          }
        ]
      },
      "transparent": false
    },
    {
      "id": 12,
      "type": "table",
      "title": "A100 GPU List",
      "description": "Health, utilisation, and economic decision for each A100 GPU",
      "gridPos": {
        "h": 14,
        "w": 9,
        "x": 15,
        "y": 8
      },
      "datasource": {
        "type": "postgres",
        "uid": "P0D1C26D7DC78F49D"
      },
      "targets": [
        {
          "refId": "A",
          "rawSql": "WITH latest_dec AS (\n  SELECT DISTINCT ON (gpu_uuid)\n    gpu_uuid, npv_keep, npv_sell, decision, health_score, rationale, confidence\n  FROM gpu_economic_decisions\n  ORDER BY gpu_uuid, time DESC\n),\nlatest_health AS (\n  SELECT DISTINCT ON (gpu_uuid) gpu_uuid, overall_score, health_grade\n  FROM gpu_health_scores ORDER BY gpu_uuid, time DESC\n),\nlatest_metrics AS (\n  SELECT DISTINCT ON (gpu_uuid) gpu_uuid, gpu_temp, sm_active\n  FROM gpu_metrics ORDER BY gpu_uuid, time DESC\n)\nSELECT\n  a.gpu_uuid AS \"UUID\",\n  h.health_grade AS \"Grade\",\n  ROUND(h.overall_score::numeric, 0) AS \"Health\",\n  EXTRACT(MONTH FROM AGE(NOW(), a.deployment_date))::int AS \"Age (mo)\",\n  ROUND(m2.gpu_temp::numeric, 1) AS \"Temp \u00b0C\",\n  ROUND((m2.sm_active)::numeric, 0) AS \"Util %\",\n  UPPER(d.decision) AS \"Decision\",\n  ROUND(d.npv_sell::numeric, 0) AS \"NPV Sell $\",\n  ROUND(d.npv_keep::numeric, 0) AS \"NPV Keep $\",\n  ROUND((d.confidence * 100)::numeric, 0) AS \"Conf %\",\n  d.rationale AS \"Analysis\"\nFROM gpu_assets a\nJOIN gpu_datacenter_mapping dm ON a.gpu_uuid = dm.gpu_uuid\nLEFT JOIN latest_dec d ON a.gpu_uuid = d.gpu_uuid\nLEFT JOIN latest_health h ON a.gpu_uuid = h.gpu_uuid\nLEFT JOIN latest_metrics m2 ON a.gpu_uuid = m2.gpu_uuid\nWHERE a.model LIKE '%A100%'\n  AND (dm.datacenter = '$datacenter' OR '$datacenter' = 'ALL')\nORDER BY h.overall_score ASC NULLS LAST",
          "format": "table"
        }
      ],
      "options": {
        "showHeader": true,
        "footer": {
          "show": false,
          "reducer": [
            "sum"
          ],
          "fields": ""
        },
        "sortBy": []
      },
      "fieldConfig": {
        "defaults": {
          "custom": {
            "align": "auto",
            "displayMode": "auto",
            "inspect": false,
            "minWidth": 50
          },
          "color": {
            "mode": "thresholds"
          },
          "mappings": [],
          "thresholds": {
            "mode": "absolute",
            "steps": [
              {
                "value": null,
                "color": "green"
              }
            ]
          }
        },
        "overrides": [
          {
            "matcher": {
              "id": "byName",
              "options": "Grade"
            },
            "properties": [
              {
                "id": "custom.displayMode",
                "value": "color-background"
              },
              {
                "id": "mappings",
                "value": [
                  {
                    "type": "value",
                    "options": {
                      "excellent": {
                        "color": "#3fb950",
                        "index": 0
                      }
                    }
                  },
                  {
                    "type": "value",
                    "options": {
                      "good": {
                        "color": "#58a6ff",
                        "index": 1
                      }
                    }
                  },
                  {
                    "type": "value",
                    "options": {
                      "fair": {
                        "color": "#d29922",
                        "index": 2
                      }
                    }
                  },
                  {
                    "type": "value",
                    "options": {
                      "degraded": {
                        "color": "#e3702d",
                        "index": 3
                      }
                    }
                  },
                  {
                    "type": "value",
                    "options": {
                      "poor": {
                        "color": "#f85149",
                        "index": 4
                      }
                    }
                  }
                ]
              }
            ]
          },
          {
            "matcher": {
              "id": "byName",
              "options": "Decision"
            },
            "properties": [
              {
                "id": "custom.displayMode",
                "value": "color-background"
              },
              {
                "id": "mappings",
                "value": [
                  {
                    "type": "value",
                    "options": {
                      "KEEP": {
                        "color": "#1f6feb",
                        "index": 0
                      }
                    }
                  },
                  {
                    "type": "value",
                    "options": {
                      "SELL": {
                        "color": "#f85149",
                        "index": 1
                      }
                    }
                  },
                  {
                    "type": "value",
                    "options": {
                      "REPURPOSE": {
                        "color": "#bc8cff",
                        "index": 2
                      }
                    }
                  }
                ]
              }
            ]
          },
          {
            "matcher": {
              "id": "byName",
              "options": "Health"
            },
            "properties": [
              {
                "id": "unit",
                "value": "short"
              },
              {
                "id": "thresholds",
                "value": {
                  "mode": "absolute",
                  "steps": [
                    {
                      "value": null,
                      "color": "#f85149"
                    },
                    {
                      "value": 70,
                      "color": "#d29922"
                    },
                    {
                      "value": 85,
                      "color": "#3fb950"
                    }
                  ]
                }
              },
              {
                "id": "custom.displayMode",
                "value": "color-text"
              }
            ]
          },
          {
            "matcher": {
              "id": "byName",
              "options": "NPV Sell $"
            },
            "properties": [
              {
                "id": "unit",
                "value": "currencyUSD"
              },
              {
                "id": "decimals",
                "value": 0
              }
            ]
          },
          {
            "matcher": {
              "id": "byName",
              "options": "NPV Keep $"
            },
            "properties": [
              {
                "id": "unit",
                "value": "currencyUSD"
              },
              {
                "id": "decimals",
                "value": 0
              }
            ]
          },
          {
            "matcher": {
              "id": "byName",
              "options": "Temp \u00b0C"
            },
            "properties": [
              {
                "id": "unit",
                "value": "celsius"
              },
              {
                "id": "decimals",
                "value": 1
              }
            ]
          },
          {
            "matcher": {
              "id": "byName",
              "options": "Util %"
            },
            "properties": [
              {
                "id": "unit",
                "value": "percent"
              },
              {
                "id": "decimals",
                "value": 0
              }
            ]
          },
          {
            "matcher": {
              "id": "byName",
              "options": "Analysis"
            },
            "properties": [
              {
                "id": "custom.width",
                "value": 420
              },
              {
                "id": "custom.displayMode",
                "value": "auto"
              },
              {
                "id": "custom.wrap",
                "value": true
              },
              {
                "id": "color",
                "value": {
                  "mode": "fixed",
                  "fixedColor": "text"
                }
              }
            ]
          },
          {
            "matcher": {
              "id": "byName",
              "options": "Conf %"
            },
            "properties": [
              {
                "id": "unit",
                "value": "percent"
              },
              {
                "id": "custom.width",
                "value": 65
              },
              {
                "id": "thresholds",
                "value": {
                  "mode": "absolute",
                  "steps": [
                    {
                      "color": "red",
                      "value": null
                    },
                    {
                      "color": "orange",
                      "value": 60
                    },
                    {
                      "color": "green",
                      "value": 80
                    }
                  ]
                }
              },
              {
                "id": "custom.displayMode",
                "value": "color-text"
              }
            ]
          }
        ]
      },
      "transparent": false
    },
    {
      "id": 20,
      "type": "row",
      "title": "\ud83d\udfe3 H100 \u2014 NVIDIA H100 SXM5-80GB",
      "collapsed": false,
      "gridPos": {
        "h": 1,
        "w": 24,
        "x": 0,
        "y": 18
      },
      "panels": [],
      "datasource": null
    },
    {
      "id": 21,
      "type": "barchart",
      "title": "H100 NPV vs Original Cost",
      "description": "Per-GPU comparison: original purchase cost, secondary market NPV, and operational NPV (keep value)",
      "gridPos": {
        "h": 10,
        "w": 15,
        "x": 0,
        "y": 19
      },
      "datasource": {
        "type": "postgres",
        "uid": "P0D1C26D7DC78F49D"
      },
      "targets": [
        {
          "refId": "A",
          "rawSql": "WITH latest_dec AS (\n  SELECT DISTINCT ON (gpu_uuid)\n    gpu_uuid, npv_keep, npv_sell, decision\n  FROM gpu_economic_decisions\n  ORDER BY gpu_uuid, time DESC\n),\nmkt AS (\n  SELECT DISTINCT ON (model)\n    model, price_mid_usd, original_cost_usd\n  FROM gpu_market_prices\n  WHERE condition = 'used_good'\n  ORDER BY model, fetched_at DESC\n)\nSELECT\n  a.gpu_uuid AS \"GPU\",\n  COALESCE(mp.original_cost_usd, 32000) AS \"Original Cost\",\n  ROUND(COALESCE(d.npv_sell, mp.price_mid_usd * 0.95)::numeric, 0) AS \"Secondary Market (NPV Sell)\",\n  ROUND(COALESCE(d.npv_keep, 0)::numeric, 0) AS \"Operational Value (NPV Keep)\"\nFROM gpu_assets a\nJOIN gpu_datacenter_mapping dm ON a.gpu_uuid = dm.gpu_uuid\nLEFT JOIN latest_dec d ON a.gpu_uuid = d.gpu_uuid\nLEFT JOIN mkt mp ON a.model = mp.model\nWHERE a.model LIKE '%H100%'\n  AND ('$datacenter' = 'ALL' OR dm.datacenter = '$datacenter')\nORDER BY a.gpu_uuid",
          "format": "table"
        }
      ],
      "options": {
        "xField": "GPU",
        "barWidth": 0.6,
        "groupWidth": 0.7,
        "fillOpacity": 85,
        "gradientMode": "none",
        "tooltipOptions": {
          "mode": "multi",
          "sort": "none"
        },
        "legend": {
          "displayMode": "list",
          "placement": "bottom",
          "calcs": []
        },
        "orientation": "auto",
        "stacking": "none",
        "showValue": "never",
        "barRadius": 0.03
      },
      "fieldConfig": {
        "defaults": {
          "unit": "currencyUSD",
          "decimals": 0,
          "color": {
            "mode": "fixed"
          },
          "custom": {
            "axisPlacement": "auto",
            "axisLabel": "",
            "axisColorMode": "text",
            "scaleDistribution": {
              "type": "linear"
            },
            "hideFrom": {
              "legend": false,
              "tooltip": false,
              "viz": false
            },
            "fillOpacity": 85
          }
        },
        "overrides": [
          {
            "matcher": {
              "id": "byName",
              "options": "Original Cost"
            },
            "properties": [
              {
                "id": "color",
                "value": {
                  "mode": "fixed",
                  "fixedColor": "#484f58"
                }
              },
              {
                "id": "unit",
                "value": "currencyUSD"
              },
              {
                "id": "decimals",
                "value": 0
              }
            ]
          },
          {
            "matcher": {
              "id": "byName",
              "options": "Secondary Market (NPV Sell)"
            },
            "properties": [
              {
                "id": "color",
                "value": {
                  "mode": "fixed",
                  "fixedColor": "#3fb950"
                }
              },
              {
                "id": "unit",
                "value": "currencyUSD"
              },
              {
                "id": "decimals",
                "value": 0
              }
            ]
          },
          {
            "matcher": {
              "id": "byName",
              "options": "Operational Value (NPV Keep)"
            },
            "properties": [
              {
                "id": "color",
                "value": {
                  "mode": "fixed",
                  "fixedColor": "#1f6feb"
                }
              },
              {
                "id": "unit",
                "value": "currencyUSD"
              },
              {
                "id": "decimals",
                "value": 0
              }
            ]
          }
        ]
      },
      "transparent": false
    },
    {
      "id": 22,
      "type": "table",
      "title": "H100 GPU List",
      "description": "Health, utilisation, and economic decision for each H100 GPU",
      "gridPos": {
        "h": 14,
        "w": 9,
        "x": 15,
        "y": 19
      },
      "datasource": {
        "type": "postgres",
        "uid": "P0D1C26D7DC78F49D"
      },
      "targets": [
        {
          "refId": "A",
          "rawSql": "WITH latest_dec AS (\n  SELECT DISTINCT ON (gpu_uuid)\n    gpu_uuid, npv_keep, npv_sell, decision, health_score, rationale, confidence\n  FROM gpu_economic_decisions\n  ORDER BY gpu_uuid, time DESC\n),\nlatest_health AS (\n  SELECT DISTINCT ON (gpu_uuid) gpu_uuid, overall_score, health_grade\n  FROM gpu_health_scores ORDER BY gpu_uuid, time DESC\n),\nlatest_metrics AS (\n  SELECT DISTINCT ON (gpu_uuid) gpu_uuid, gpu_temp, sm_active\n  FROM gpu_metrics ORDER BY gpu_uuid, time DESC\n)\nSELECT\n  a.gpu_uuid AS \"UUID\",\n  h.health_grade AS \"Grade\",\n  ROUND(h.overall_score::numeric, 0) AS \"Health\",\n  EXTRACT(MONTH FROM AGE(NOW(), a.deployment_date))::int AS \"Age (mo)\",\n  ROUND(m2.gpu_temp::numeric, 1) AS \"Temp \u00b0C\",\n  ROUND((m2.sm_active)::numeric, 0) AS \"Util %\",\n  UPPER(d.decision) AS \"Decision\",\n  ROUND(d.npv_sell::numeric, 0) AS \"NPV Sell $\",\n  ROUND(d.npv_keep::numeric, 0) AS \"NPV Keep $\",\n  ROUND((d.confidence * 100)::numeric, 0) AS \"Conf %\",\n  d.rationale AS \"Analysis\"\nFROM gpu_assets a\nJOIN gpu_datacenter_mapping dm ON a.gpu_uuid = dm.gpu_uuid\nLEFT JOIN latest_dec d ON a.gpu_uuid = d.gpu_uuid\nLEFT JOIN latest_health h ON a.gpu_uuid = h.gpu_uuid\nLEFT JOIN latest_metrics m2 ON a.gpu_uuid = m2.gpu_uuid\nWHERE a.model LIKE '%H100%'\n  AND (dm.datacenter = '$datacenter' OR '$datacenter' = 'ALL')\nORDER BY h.overall_score ASC NULLS LAST",
          "format": "table"
        }
      ],
      "options": {
        "showHeader": true,
        "footer": {
          "show": false,
          "reducer": [
            "sum"
          ],
          "fields": ""
        },
        "sortBy": []
      },
      "fieldConfig": {
        "defaults": {
          "custom": {
            "align": "auto",
            "displayMode": "auto",
            "inspect": false,
            "minWidth": 50
          },
          "color": {
            "mode": "thresholds"
          },
          "mappings": [],
          "thresholds": {
            "mode": "absolute",
            "steps": [
              {
                "value": null,
                "color": "green"
              }
            ]
          }
        },
        "overrides": [
          {
            "matcher": {
              "id": "byName",
              "options": "Grade"
            },
            "properties": [
              {
                "id": "custom.displayMode",
                "value": "color-background"
              },
              {
                "id": "mappings",
                "value": [
                  {
                    "type": "value",
                    "options": {
                      "excellent": {
                        "color": "#3fb950",
                        "index": 0
                      }
                    }
                  },
                  {
                    "type": "value",
                    "options": {
                      "good": {
                        "color": "#58a6ff",
                        "index": 1
                      }
                    }
                  },
                  {
                    "type": "value",
                    "options": {
                      "fair": {
                        "color": "#d29922",
                        "index": 2
                      }
                    }
                  },
                  {
                    "type": "value",
                    "options": {
                      "degraded": {
                        "color": "#e3702d",
                        "index": 3
                      }
                    }
                  },
                  {
                    "type": "value",
                    "options": {
                      "poor": {
                        "color": "#f85149",
                        "index": 4
                      }
                    }
                  }
                ]
              }
            ]
          },
          {
            "matcher": {
              "id": "byName",
              "options": "Decision"
            },
            "properties": [
              {
                "id": "custom.displayMode",
                "value": "color-background"
              },
              {
                "id": "mappings",
                "value": [
                  {
                    "type": "value",
                    "options": {
                      "KEEP": {
                        "color": "#1f6feb",
                        "index": 0
                      }
                    }
                  },
                  {
                    "type": "value",
                    "options": {
                      "SELL": {
                        "color": "#f85149",
                        "index": 1
                      }
                    }
                  },
                  {
                    "type": "value",
                    "options": {
                      "REPURPOSE": {
                        "color": "#bc8cff",
                        "index": 2
                      }
                    }
                  }
                ]
              }
            ]
          },
          {
            "matcher": {
              "id": "byName",
              "options": "Health"
            },
            "properties": [
              {
                "id": "unit",
                "value": "short"
              },
              {
                "id": "thresholds",
                "value": {
                  "mode": "absolute",
                  "steps": [
                    {
                      "value": null,
                      "color": "#f85149"
                    },
                    {
                      "value": 70,
                      "color": "#d29922"
                    },
                    {
                      "value": 85,
                      "color": "#3fb950"
                    }
                  ]
                }
              },
              {
                "id": "custom.displayMode",
                "value": "color-text"
              }
            ]
          },
          {
            "matcher": {
              "id": "byName",
              "options": "NPV Sell $"
            },
            "properties": [
              {
                "id": "unit",
                "value": "currencyUSD"
              },
              {
                "id": "decimals",
                "value": 0
              }
            ]
          },
          {
            "matcher": {
              "id": "byName",
              "options": "NPV Keep $"
            },
            "properties": [
              {
                "id": "unit",
                "value": "currencyUSD"
              },
              {
                "id": "decimals",
                "value": 0
              }
            ]
          },
          {
            "matcher": {
              "id": "byName",
              "options": "Temp \u00b0C"
            },
            "properties": [
              {
                "id": "unit",
                "value": "celsius"
              },
              {
                "id": "decimals",
                "value": 1
              }
            ]
          },
          {
            "matcher": {
              "id": "byName",
              "options": "Util %"
            },
            "properties": [
              {
                "id": "unit",
                "value": "percent"
              },
              {
                "id": "decimals",
                "value": 0
              }
            ]
          },
          {
            "matcher": {
              "id": "byName",
              "options": "Analysis"
            },
            "properties": [
              {
                "id": "custom.width",
                "value": 420
              },
              {
                "id": "custom.displayMode",
                "value": "auto"
              },
              {
                "id": "custom.wrap",
                "value": true
              },
              {
                "id": "color",
                "value": {
                  "mode": "fixed",
                  "fixedColor": "text"
                }
              }
            ]
          },
          {
            "matcher": {
              "id": "byName",
              "options": "Conf %"
            },
            "properties": [
              {
                "id": "unit",
                "value": "percent"
              },
              {
                "id": "custom.width",
                "value": 65
              },
              {
                "id": "thresholds",
                "value": {
                  "mode": "absolute",
                  "steps": [
                    {
                      "color": "red",
                      "value": null
                    },
                    {
                      "color": "orange",
                      "value": 60
                    },
                    {
                      "color": "green",
                      "value": 80
                    }
                  ]
                }
              },
              {
                "id": "custom.displayMode",
                "value": "color-text"
              }
            ]
          }
        ]
      },
      "transparent": false
    },
    {
      "id": 30,
      "type": "row",
      "title": "\ud83d\udcca Market Intelligence",
      "collapsed": false,
      "gridPos": {
        "h": 1,
        "w": 24,
        "x": 0,
        "y": 29
      },
      "panels": [],
      "datasource": null
    },
    {
      "id": 31,
      "type": "gauge",
      "title": "A100 Depreciation",
      "description": "How far the A100 has fallen from its original new-market price",
      "gridPos": {
        "h": 6,
        "w": 6,
        "x": 0,
        "y": 30
      },
      "datasource": {
        "type": "postgres",
        "uid": "P0D1C26D7DC78F49D"
      },
      "targets": [
        {
          "refId": "A",
          "rawSql": "SELECT NOW() as time, ROUND(((original_cost_usd - price_mid_usd) / original_cost_usd * 100)::numeric, 1) AS value FROM v_latest_market_prices WHERE model LIKE '%A100%' AND condition = 'used_good' LIMIT 1",
          "format": "table"
        }
      ],
      "options": {
        "reduceOptions": {
          "values": false,
          "calcs": [
            "lastNotNull"
          ],
          "fields": ""
        },
        "orientation": "auto",
        "showThresholdLabels": false,
        "showThresholdMarkers": true,
        "minVizWidth": 75,
        "minVizHeight": 75
      },
      "fieldConfig": {
        "defaults": {
          "unit": "percent",
          "decimals": 1,
          "min": 0,
          "max": 100,
          "color": {
            "mode": "thresholds"
          },
          "thresholds": {
            "mode": "absolute",
            "steps": [
              {
                "value": null,
                "color": "#3fb950"
              },
              {
                "value": 30,
                "color": "#d29922"
              },
              {
                "value": 50,
                "color": "#e3702d"
              },
              {
                "value": 70,
                "color": "#f85149"
              }
            ]
          },
          "mappings": []
        },
        "overrides": []
      },
      "transparent": false
    },
    {
      "id": 32,
      "type": "gauge",
      "title": "H100 Depreciation",
      "description": "How far the H100 has fallen from its original new-market price",
      "gridPos": {
        "h": 6,
        "w": 6,
        "x": 6,
        "y": 30
      },
      "datasource": {
        "type": "postgres",
        "uid": "P0D1C26D7DC78F49D"
      },
      "targets": [
        {
          "refId": "A",
          "rawSql": "SELECT NOW() as time, ROUND(((original_cost_usd - price_mid_usd) / original_cost_usd * 100)::numeric, 1) AS value FROM v_latest_market_prices WHERE model LIKE '%H100%' AND condition = 'used_good' LIMIT 1",
          "format": "table"
        }
      ],
      "options": {
        "reduceOptions": {
          "values": false,
          "calcs": [
            "lastNotNull"
          ],
          "fields": ""
        },
        "orientation": "auto",
        "showThresholdLabels": false,
        "showThresholdMarkers": true,
        "minVizWidth": 75,
        "minVizHeight": 75
      },
      "fieldConfig": {
        "defaults": {
          "unit": "percent",
          "decimals": 1,
          "min": 0,
          "max": 100,
          "color": {
            "mode": "thresholds"
          },
          "thresholds": {
            "mode": "absolute",
            "steps": [
              {
                "value": null,
                "color": "#3fb950"
              },
              {
                "value": 30,
                "color": "#d29922"
              },
              {
                "value": 50,
                "color": "#e3702d"
              },
              {
                "value": 70,
                "color": "#f85149"
              }
            ]
          },
          "mappings": []
        },
        "overrides": []
      },
      "transparent": false
    },
    {
      "id": 33,
      "type": "timeseries",
      "title": "Market Price Trend (A100)",
      "description": "A100 secondary market mid-price over the last 7 days",
      "gridPos": {
        "h": 6,
        "w": 12,
        "x": 12,
        "y": 30
      },
      "datasource": {
        "type": "postgres",
        "uid": "P0D1C26D7DC78F49D"
      },
      "targets": [
        {
          "refId": "A",
          "rawSql": "SELECT fetched_at AS \"time\", price_mid_usd AS \"A100 Mid Price\", price_low_usd AS \"A100 Low\", price_high_usd AS \"A100 High\" FROM gpu_market_prices WHERE model LIKE '%A100%' AND condition = 'used_good' AND fetched_at >= NOW() - INTERVAL '7 days' ORDER BY fetched_at ASC",
          "format": "time_series"
        }
      ],
      "options": {
        "tooltip": {
          "mode": "multi",
          "sort": "none"
        },
        "legend": {
          "displayMode": "list",
          "placement": "bottom",
          "calcs": []
        }
      },
      "fieldConfig": {
        "defaults": {
          "unit": "currencyUSD",
          "decimals": 0,
          "color": {
            "mode": "palette-classic"
          },
          "custom": {
            "drawStyle": "line",
            "lineInterpolation": "smooth",
            "barAlignment": 0,
            "lineWidth": 2,
            "fillOpacity": 10,
            "gradientMode": "none",
            "spanNulls": false,
            "showPoints": "auto",
            "pointSize": 5,
            "stacking": {
              "mode": "none",
              "group": "A"
            },
            "axisPlacement": "auto",
            "axisLabel": "",
            "axisColorMode": "text",
            "scaleDistribution": {
              "type": "linear"
            },
            "axisCenteredZero": false,
            "hideFrom": {
              "legend": false,
              "tooltip": false,
              "viz": false
            },
            "thresholdsStyle": {
              "mode": "off"
            }
          },
          "thresholds": {
            "mode": "absolute",
            "steps": [
              {
                "value": null,
                "color": "green"
              }
            ]
          },
          "mappings": []
        },
        "overrides": [
          {
            "matcher": {
              "id": "byName",
              "options": "A100 Mid Price"
            },
            "properties": [
              {
                "id": "color",
                "value": {
                  "mode": "fixed",
                  "fixedColor": "#3fb950"
                }
              },
              {
                "id": "custom.lineWidth",
                "value": 2
              }
            ]
          },
          {
            "matcher": {
              "id": "byName",
              "options": "A100 Low"
            },
            "properties": [
              {
                "id": "color",
                "value": {
                  "mode": "fixed",
                  "fixedColor": "#484f58"
                }
              },
              {
                "id": "custom.lineWidth",
                "value": 1
              },
              {
                "id": "custom.lineStyle",
                "value": {
                  "fill": "dash",
                  "dash": [
                    4,
                    4
                  ]
                }
              }
            ]
          },
          {
            "matcher": {
              "id": "byName",
              "options": "A100 High"
            },
            "properties": [
              {
                "id": "color",
                "value": {
                  "mode": "fixed",
                  "fixedColor": "#484f58"
                }
              },
              {
                "id": "custom.lineWidth",
                "value": 1
              },
              {
                "id": "custom.lineStyle",
                "value": {
                  "fill": "dash",
                  "dash": [
                    4,
                    4
                  ]
                }
              }
            ]
          }
        ]
      },
      "transparent": false
    }
  ],
  "refresh": "5m",
  "schemaVersion": 38,
  "style": "dark",
  "tags": [
    "gpu",
    "economics",
    "secondary-market"
  ],
  "templating": {
    "list": [
      {
        "current": {
          "selected": true,
          "text": "All",
          "value": "$__all"
        },
        "datasource": {
          "type": "postgres",
          "uid": "P0D1C26D7DC78F49D"
        },
        "definition": "SELECT DISTINCT datacenter FROM gpu_datacenter_mapping ORDER BY datacenter",
        "hide": 0,
        "includeAll": true,
        "allValue": "ALL",
        "label": "Data Centre",
        "multi": false,
        "name": "datacenter",
        "options": [],
        "query": "SELECT DISTINCT datacenter FROM gpu_datacenter_mapping ORDER BY datacenter",
        "refresh": 2,
        "regex": "",
        "sort": 1,
        "type": "query"
      }
    ]
  },
  "time": {
    "from": "now-24h",
    "to": "now"
  },
  "timepicker": {},
  "timezone": "browser",
  "title": "GPU Fleet Economics \u00b7 Secondary Market",
  "uid": "gpu-secondary-market",
  "version": 1,
  "weekStart": ""
}